procxx/__init__.py
procxx/procxx.py
procxx-0.1.dist-info/LICENSE
procxx-0.1.dist-info/METADATA
procxx-0.1.dist-info/WHEEL
procxx-0.1.dist-info/top_level.txt
procxx-0.1.dist-info/RECORD
