Metadata-Version: 2.1
Name: procxx
Version: 0.1
Summary: Small C++ builder tools
Home-page: https://github.com/xp-op/procxx
Author: Xp
Author-email: breakdowneternity@gmail.com
License: MIT
Project-URL: Bug Tracker, https://github.com/xp-op/procxx/issues
Platform: UNKNOWN
Classifier: Programming Language :: Python :: 3
Classifier: License :: OSI Approved :: MIT License
Classifier: Operating System :: OS Independent
Requires-Python: >=3.10
License-File: LICENSE
